huggingsound/__init__.py
huggingsound/metrics.py
huggingsound/normalizer.py
huggingsound/speech_classification/__init__.py
huggingsound/speech_recognition/__init__.py
huggingsound/speech_recognition/decoder.py
huggingsound/speech_recognition/model.py
huggingsound/token_set.py
huggingsound/trainer.py
huggingsound/utils.py
huggingsound-0.1.6.dist-info/LICENSE
huggingsound-0.1.6.dist-info/WHEEL
huggingsound-0.1.6.dist-info/METADATA
huggingsound-0.1.6.dist-info/RECORD
