Metadata-Version: 2.1
Name: huggingsound
Version: 0.1.6
Summary: HuggingSound: A toolkit for speech-related tasks based on HuggingFace's tools.
Home-page: https://github.com/jonatasgrosman/huggingsound
License: MIT
Keywords: transformers,audio,speech,automatic speech recognition,asr,voice recognition,speech recognition,speech-to-text
Author: Jonatas Grosman
Author-email: jonatasgrosman@gmail.com
Maintainer: Jonatas Grosman
Maintainer-email: jonatasgrosman@gmail.com
Requires-Python: >=3.7,<4
Classifier: License :: OSI Approved :: MIT License
Classifier: Programming Language :: Python :: 3
Classifier: Programming Language :: Python :: 3.7
Classifier: Programming Language :: Python :: 3.8
Classifier: Programming Language :: Python :: 3.9
Classifier: Programming Language :: Python :: 3.10
Classifier: Programming Language :: Python :: 3.11
Requires-Dist: datasets (>=2.6.1,<3.0.0)
Requires-Dist: jiwer (>=2.5.1,<3.0.0)
Requires-Dist: librosa (>=0.9.2,<0.10.0)
Requires-Dist: torch (>=1.7,!=1.12.0,<1.13.0)
Requires-Dist: transformers (>=4.23.1,<5.0.0)
Project-URL: Documentation, https://github.com/jonatasgrosman/huggingsound
Project-URL: Repository, https://github.com/jonatasgrosman/huggingsound
Project-URL: issues, https://github.com/jonatasgrosman/huggingsound/issues
